pysonic_channel-0.1.2.dist-info/METADATA
pysonic_channel-0.1.2.dist-info/WHEEL
sonic/sonic.pyi
sonic/__init__.py
sonic/sonic.pypy39-pp73-x86_64-linux-gnu.so
pysonic_channel-0.1.2.dist-info/RECORD
