Metadata-Version: 2.1
Name: pysonic_channel
Version: 0.1.2
Classifier: Programming Language :: Rust
Classifier: Programming Language :: Python :: Implementation :: CPython
Classifier: Programming Language :: Python :: Implementation :: PyPy
Summary: Python client for sonic search backend
Keywords: sonic,search,client,elasticsearch,api
Home-Page: https://github.com/alongwy/pysonic
Author: ylfeng <ylfeng@ir.hit.edu.cn>
Author-email: ylfeng <ylfeng@ir.hit.edu.cn>
License: MPL-2.0
Requires-Python: >=3.7
Project-URL: Source Code, https://github.com/alongwy/pysonic
